{
  "url": "https://hdporncomics.com/api/v1/user/favorites?page=1",
  "nexturl": null,
  "page": 1,
  "lastpage": 1,
  "posts": [
    {
      "type": "Comic",
      "id": 216362,
      "title": "Nights In Ludos 3 - Surprises",
      "link": "https://hdporncomics.com/nights-in-ludos-3-surprises-albatross-sex-comic/",
      "cover": "https://e.hdporncomics.com/thumbs/3161610/001.jpg",
      "views": 28587,
      "likes": 42,
      "dlikes": 11,
      "favorites": 134,
      "comments": 5,
      "created": "2025-03-19T18:32:19.000000Z",
      "modified": "2025-03-19T18:32:19.000000Z"
    },
    {
      "type": "Comic",
      "id": 215852,
      "title": "Hokago wa 18-gou Sanchi de Sex Sammai | Having SEX at No.18-san's House After School",
      "link": "https://hdporncomics.com/hokago-wa-18-gou-sanchi-de-sex-sammai-having-sex-at-no-18-san-s-house-after-school-group-sex-netorare-cheating-mature-superheroes-tv-movies-sex-comic/",
      "cover": "https://l.hdporncomics.com/thumbs/e199ec5ee64a88e461cf50feb555c683/hokago-wa-18-gou-sanchi-de-sex-sammai-having-sex-at-no-18-san-s-house-after-school-001.jpg",
      "views": 56976,
      "likes": 144,
      "dlikes": 13,
      "favorites": 696,
      "comments": 10,
      "created": "2025-03-19T10:05:00.000000Z",
      "modified": "2025-03-19T10:05:00.000000Z"
    },
    {
      "type": "Comic",
      "id": 216204,
      "title": "Diana's Treasure",
      "link": "https://hdporncomics.com/diana-s-treasure-beck-cartoons-sex-comic/",
      "cover": "https://e.hdporncomics.com/thumbs/3152614/001.jpg",
      "views": 19862,
      "likes": 48,
      "dlikes": 7,
      "favorites": 225,
      "comments": 14,
      "created": "2025-03-19T20:10:40.000000Z",
      "modified": "2025-03-19T20:10:40.000000Z"
    },
    {
      "type": "Comic",
      "id": 216264,
      "title": "My Boss Is A Massive Bitch But She's A Dullahan Nymphomaniac 1",
      "link": "https://hdporncomics.com/my-boss-is-a-massive-bitch-but-she-s-a-dullahan-nymphomaniac-1-iwillbuckyou-sex-comic/",
      "cover": "https://e.hdporncomics.com/thumbs/3145014/001.jpg",
      "views": 55621,
      "likes": 111,
      "dlikes": 8,
      "favorites": 555,
      "comments": 21,
      "created": "2025-03-19T18:29:56.000000Z",
      "modified": "2025-03-19T18:29:56.000000Z"
    },
    {
      "type": "Comic",
      "id": 72466,
      "title": "[Zummeng] Tree of Life - Book 1 (Ongoing)",
      "link": "https://hdporncomics.com/zummeng-tree-of-life-book-1-ongoing-furries-western-sex-comic/",
      "cover": "https://l.hdporncomics.com/thumbs/ca0378c1b98811dbae629628edfc450a/zummeng-tree-of-life-book-1-ongoing-001.jpg",
      "views": 316083,
      "likes": 1039,
      "dlikes": 288,
      "favorites": 1039,
      "comments": 320,
      "created": "2022-05-18T06:00:00.000000Z",
      "modified": "2022-05-18T06:00:00.000000Z"
    },
    {
      "type": "Comic",
      "id": 215713,
      "title": "Hypnosis On A Chilling Night",
      "link": "https://hdporncomics.com/hypnosis-on-a-chilling-night-dedlinx-sex-comic/",
      "cover": "https://e.hdporncomics.com/thumbs/3120338/001.jpg",
      "views": 47794,
      "likes": 181,
      "dlikes": 8,
      "favorites": 639,
      "comments": 25,
      "created": "2025-03-14T01:00:00.000000Z",
      "modified": "2025-03-14T01:00:00.000000Z"
    }
  ]
}
